pytest_hylang/__init__.py
pytest_hylang/conftest.py
pytest_hylang-0.0.1.dist-info/LICENSE
pytest_hylang-0.0.1.dist-info/METADATA
pytest_hylang-0.0.1.dist-info/WHEEL
pytest_hylang-0.0.1.dist-info/entry_points.txt
pytest_hylang-0.0.1.dist-info/top_level.txt
pytest_hylang-0.0.1.dist-info/RECORD
